{
    "system_name": "Cities",
    "name_single": "City",
    "short_description": "Cities",
    "php_postsavehook": "",
    "php_before_save": "[CUSTOMCODE=saveGUIDPower]",
    "php_getlistquery": "",
    "php_getitems": "",
    "ajax_input": null,
    "source": 2,
    "icon": "images\/vdm\/icon\/city.png#joomlaImage:\/\/local-images\/vdm\/icon\/city.png?width=128&height=128",
    "php_batchmove": "",
    "add_fadein": 1,
    "description": "",
    "icon_category": "",
    "icon_add": "",
    "php_allowedit": "",
    "php_after_delete": "",
    "php_after_cancel": "",
    "type": 1,
    "php_after_publish": "",
    "mysql_table_charset": "utf8mb4",
    "name_list": "Cities",
    "addpermissions": {
        "addpermissions0": {
            "action": "view.edit",
            "implementation": 3
        },
        "addpermissions1": {
            "action": "view.edit.own",
            "implementation": 3
        },
        "addpermissions2": {
            "action": "view.edit.state",
            "implementation": 3
        },
        "addpermissions3": {
            "action": "view.edit.access",
            "implementation": 3
        },
        "addpermissions4": {
            "action": "view.edit.created_by",
            "implementation": 3
        },
        "addpermissions5": {
            "action": "view.edit.created",
            "implementation": 3
        },
        "addpermissions6": {
            "action": "view.create",
            "implementation": 3
        },
        "addpermissions7": {
            "action": "view.delete",
            "implementation": 3
        },
        "addpermissions8": {
            "action": "view.access",
            "implementation": 3
        }
    },
    "php_getitem": "",
    "php_getitems_after_all": "",
    "addtabs": null,
    "php_getform": "[CUSTOMCODE=setGUIDFormPower]",
    "php_save": "",
    "php_allowadd": "",
    "addlinked_views": null,
    "php_before_cancel": "",
    "php_batchcopy": "",
    "alias_builder_type": 1,
    "php_before_publish": "",
    "php_before_delete": "",
    "php_document": "",
    "alias_builder": null,
    "mysql_table_row_format": "DYNAMIC",
    "sql": "--\r\n-- Dumping data for table `#__[[[component]]]_city`\r\n--\r\n\r\nINSERT INTO `#__[[[component]]]_city` (`id`, `name`, `latitude`, `longitude`, `guid`, `wikidataid`, `metakey`, `metadesc`, `metadata`, `ordering`, `published`, `modified`, `created`, `hits`, `version`, `params`, `state`) VALUES\r\n(1, 'Windhoek', -22.55941000, 17.08323000, 'bbb0d564-ce06-44d3-8a1f-d5e57f56b113', 'Q3935', '', '', '{\\\"robots\\\":\\\"\\\",\\\"author\\\":\\\"\\\",\\\"rights\\\":\\\"\\\"}', 1, 1, '2025-03-27 06:27:39', '2025-03-25 16:15:07', '', 3, '', 'c840c5ae-d384-4847-b50d-a82ef2983c4d'),\r\n(2, 'Katutura', -22.52306000, 17.06028000, '242767e2-b762-49c3-86f3-f20b0c31782a', 'Q864100', '', '', '{\\\"robots\\\":\\\"\\\",\\\"author\\\":\\\"\\\",\\\"rights\\\":\\\"\\\"}', '', 1, '2025-03-27 06:27:30', '2025-03-26 14:33:30', '', 2, '', 'c840c5ae-d384-4847-b50d-a82ef2983c4d'),\r\n(3, 'Grootfontein', -19.56667000, 18.11667000, '6f134147-6248-4a80-b3f2-8b8fe5dadaf8', 'Q986336', '', '', '{\\\"robots\\\":\\\"\\\",\\\"author\\\":\\\"\\\",\\\"rights\\\":\\\"\\\"}', '', 1, '2025-03-27 06:27:21', '2025-03-26 15:44:11', '', 2, '', 'de577325-1ded-46d9-a02c-231bcd8a461e'),\r\n(4, 'Okahandja', -21.98333000, 16.91667000, '30c4b604-a6bb-4eba-a0a4-976ea0f72183', 'Q597491', '', '', '{\\\"robots\\\":\\\"\\\",\\\"author\\\":\\\"\\\",\\\"rights\\\":\\\"\\\"}', '', 1, '2025-03-27 06:27:14', '2025-03-26 15:44:11', '', 2, '', 'de577325-1ded-46d9-a02c-231bcd8a461e'),\r\n(5, 'Okakarara', -20.58333000, 17.43333000, 'e1029056-9b2c-4f24-8f85-6d77aa59d247', 'Q992077', '', '', '{\\\"robots\\\":\\\"\\\",\\\"author\\\":\\\"\\\",\\\"rights\\\":\\\"\\\"}', '', 1, '2025-03-27 06:27:04', '2025-03-26 15:44:11', '', 2, '', 'de577325-1ded-46d9-a02c-231bcd8a461e'),\r\n(6, 'Otavi', -19.65000000, 17.33333000, '7c63b580-4ee0-499f-b34b-efbc4675bff6', 'Q1013965', '', '', '{\\\"robots\\\":\\\"\\\",\\\"author\\\":\\\"\\\",\\\"rights\\\":\\\"\\\"}', '', 1, '2025-03-27 06:26:56', '2025-03-26 15:44:11', '', 2, '', 'de577325-1ded-46d9-a02c-231bcd8a461e'),\r\n(7, 'Otjiwarongo', -20.46369000, 16.64772000, '4ed6c60e-5e13-4d68-83e8-5e2f5e6d0a75', 'Q993149', '', '', '{\\\"robots\\\":\\\"\\\",\\\"author\\\":\\\"\\\",\\\"rights\\\":\\\"\\\"}', '', 1, '2025-03-27 06:26:43', '2025-03-26 15:44:11', '', 2, '', 'de577325-1ded-46d9-a02c-231bcd8a461e'),\r\n(46, 'Arandis', -22.41667000, 14.96667000, 'f17e54f0-e05d-43cd-98ef-5bedeaa554d2', 'Q438851', '', '', '{\\\"robots\\\":\\\"\\\",\\\"author\\\":\\\"\\\",\\\"rights\\\":\\\"\\\"}', '', 1, '2025-03-27 06:26:07', '2025-03-26 15:56:53', '', 2, '', '2c0377c7-dd30-4a67-b8b9-7ce1aff4ff9b'),\r\n(47, 'Hentiesbaai', -22.11667000, 14.28333000, 'c293ed83-c69c-4b7f-a271-7e50eacd134b', 'Q1013389', '', '', '{\\\"robots\\\":\\\"\\\",\\\"author\\\":\\\"\\\",\\\"rights\\\":\\\"\\\"}', '', 1, '2025-03-27 06:26:00', '2025-03-26 15:56:53', '', 2, '', '2c0377c7-dd30-4a67-b8b9-7ce1aff4ff9b'),\r\n(48, 'Karibib', -21.93333000, 15.83333000, '53a9d49b-a0ef-4e7e-ad67-7ea09c517981', 'Q1348181', '', '', '{\\\"robots\\\":\\\"\\\",\\\"author\\\":\\\"\\\",\\\"rights\\\":\\\"\\\"}', '', 1, '2025-03-27 06:25:51', '2025-03-26 15:56:53', '', 2, '', '2c0377c7-dd30-4a67-b8b9-7ce1aff4ff9b'),\r\n(49, 'Omaruru', -21.43333000, 15.93333000, 'da8b47b0-817d-4490-87d3-4975bb540468', 'Q1896161', '', '', '{\\\"robots\\\":\\\"\\\",\\\"author\\\":\\\"\\\",\\\"rights\\\":\\\"\\\"}', '', 1, '2025-03-27 06:25:41', '2025-03-26 15:56:53', '', 2, '', '2c0377c7-dd30-4a67-b8b9-7ce1aff4ff9b'),\r\n(50, 'Otjimbingwe', -22.35000000, 16.13333000, 'b59c43c0-6da9-4d06-85e8-ced33440797e', 'Q464050', '', '', '{\\\"robots\\\":\\\"\\\",\\\"author\\\":\\\"\\\",\\\"rights\\\":\\\"\\\"}', '', 1, '2025-03-27 06:25:32', '2025-03-26 15:56:53', '', 2, '', '2c0377c7-dd30-4a67-b8b9-7ce1aff4ff9b'),\r\n(51, 'Swakopmund', -22.63199000, 14.60119000, '4c512316-7d59-46a6-bef9-b6095de9fd34', 'Q59698', '', '', '{\\\"robots\\\":\\\"\\\",\\\"author\\\":\\\"\\\",\\\"rights\\\":\\\"\\\"}', '', 1, '2025-03-27 06:25:17', '2025-03-26 15:56:53', '', 2, '', '2c0377c7-dd30-4a67-b8b9-7ce1aff4ff9b'),\r\n(52, 'Swakopmund Constituency', -22.63199000, 14.60119000, '225d5064-17d3-4ca7-9970-3f99a4cd0d54', 'Q3711710', '', '', '{\\\"robots\\\":\\\"\\\",\\\"author\\\":\\\"\\\",\\\"rights\\\":\\\"\\\"}', '', 1, '2025-03-27 06:25:10', '2025-03-26 15:56:53', '', 2, '', '2c0377c7-dd30-4a67-b8b9-7ce1aff4ff9b'),\r\n(53, 'Usakos', -22.00000000, 15.60000000, '36700f6c-cb0a-4058-a8dc-06ebf08cb778', 'Q1457265', '', '', '{\\\"robots\\\":\\\"\\\",\\\"author\\\":\\\"\\\",\\\"rights\\\":\\\"\\\"}', '', 1, '2025-03-27 06:25:02', '2025-03-26 15:56:53', '', 2, '', '2c0377c7-dd30-4a67-b8b9-7ce1aff4ff9b'),\r\n(54, 'Walvis Bay', -22.95750000, 14.50528000, '88d88df9-becc-4889-92f1-1583bf5527cc', 'Q220843', '', '', '{\\\"robots\\\":\\\"\\\",\\\"author\\\":\\\"\\\",\\\"rights\\\":\\\"\\\"}', '', 1, '2025-03-27 06:24:55', '2025-03-26 15:56:53', '', 2, '', '2c0377c7-dd30-4a67-b8b9-7ce1aff4ff9b'),\r\n(55, 'Aranos', -24.13333000, 19.11667000, 'd6f24f64-b251-40a6-b788-fa60bee19ad0', 'Q626040', '', '', '{\\\"robots\\\":\\\"\\\",\\\"author\\\":\\\"\\\",\\\"rights\\\":\\\"\\\"}', '', 1, '2025-03-27 06:24:49', '2025-03-26 20:41:21', '', 2, '', 'a6e7f963-5288-423a-b9fb-6e92b9fba241'),\r\n(56, 'Hoachanas', -23.91667000, 18.05000000, 'd735b369-eaaa-4f51-9443-d5d3dbefa40b', 'Q1621498', '', '', '{\\\"robots\\\":\\\"\\\",\\\"author\\\":\\\"\\\",\\\"rights\\\":\\\"\\\"}', '', 1, '2025-03-27 06:24:41', '2025-03-26 20:41:21', '', 2, '', 'a6e7f963-5288-423a-b9fb-6e92b9fba241'),\r\n(57, 'Maltah\u00f6he', -24.83333000, 16.98333000, '80ca95e5-cc9b-406d-84b4-aafde00185ca', 'Q666079', '', '', '{\\\"robots\\\":\\\"\\\",\\\"author\\\":\\\"\\\",\\\"rights\\\":\\\"\\\"}', '', 1, '2025-03-27 06:24:34', '2025-03-26 20:41:21', '', 3, '', 'a6e7f963-5288-423a-b9fb-6e92b9fba241'),\r\n(58, 'Mariental', -24.63333000, 17.96667000, '593d2071-0a8d-4135-876f-ac57108add56', 'Q876166', '', '', '{\\\"robots\\\":\\\"\\\",\\\"author\\\":\\\"\\\",\\\"rights\\\":\\\"\\\"}', '', 1, '2025-03-27 06:24:23', '2025-03-26 20:41:21', '', 2, '', 'a6e7f963-5288-423a-b9fb-6e92b9fba241'),\r\n(59, 'Rehoboth', -23.31700000, 17.09000000, 'ef026966-e25a-4237-a5fc-fdcd3b1e8055', 'Q700050', '', '', '{\\\"robots\\\":\\\"\\\",\\\"author\\\":\\\"\\\",\\\"rights\\\":\\\"\\\"}', '', 1, '2025-03-27 06:21:06', '2025-03-26 20:41:21', '', 4, '', 'a6e7f963-5288-423a-b9fb-6e92b9fba241'),\r\n(163, 'Johannesburg', -26.20227000, 28.04363000, '4882dea0-5ff7-4e7b-a0e8-90d5baab5c04', 'Q34647', '', '', '', '', 1, '', '2025-03-27 20:04:29', '', 1, '', '9fdce875-06ed-4498-964e-0f723631fe1f'),\r\n(164, 'Bethanie', -26.48333000, 17.15000000, '63927a1f-531f-4a18-9013-48fc892ac07e', 'Q251677', '', '', '', '', 1, '', '2025-03-28 08:42:37', '', 1, '', 'cc07c55b-ffe4-43b3-97b7-23b5746c09f9'),\r\n(165, 'Karasburg', -28.01667000, 18.75000000, '25d67ad8-f33c-44e2-ab11-7ad06b6c67a5', 'Q1003328', '', '', '', '', 1, '', '2025-03-28 08:42:37', '', 1, '', 'cc07c55b-ffe4-43b3-97b7-23b5746c09f9'),\r\n(166, 'Keetmanshoop', -26.58333000, 18.13333000, '82f3fc6d-0fa5-4d1a-9a06-156ad308f930', 'Q160884', '', '', '', '', 1, '', '2025-03-28 08:42:37', '', 1, '', 'cc07c55b-ffe4-43b3-97b7-23b5746c09f9'),\r\n(167, 'L\u00fcderitz', -26.64807000, 15.15383000, 'd894e23f-da26-4ed1-a4f1-5234a084c5fd', 'Q159325', '', '', '', '', 1, '', '2025-03-28 08:42:37', '', 1, '', 'cc07c55b-ffe4-43b3-97b7-23b5746c09f9'),\r\n(168, 'Oranjemund', -28.55000000, 16.43333000, 'fc9309eb-ba1a-4252-98c0-4136abec821b', 'Q1404518', '', '', '', '', 1, '', '2025-03-28 08:42:37', '', 1, '', 'cc07c55b-ffe4-43b3-97b7-23b5746c09f9'),\r\n(169, 'Tses', -25.88333000, 18.00000000, '34917941-8bbf-4036-ba37-d9a013f2a615', 'Q1529444', '', '', '', '', 1, '', '2025-03-28 08:42:37', '', 1, '', 'cc07c55b-ffe4-43b3-97b7-23b5746c09f9'),\r\n(170, 'Warmbad', -28.45000000, 18.73333000, 'f95496cc-6e66-43c4-a689-49e4ee7ba34f', 'Q479312', '', '', '', '', 1, '', '2025-03-28 08:42:37', '', 1, '', 'cc07c55b-ffe4-43b3-97b7-23b5746c09f9'),\r\n(171, 'Rundu', -17.93333000, 19.76667000, '9a544557-e9d5-4bb9-85bb-dcfb106f75c1', 'Q662291', '', '', '', '', 1, '', '2025-03-28 08:45:12', '', 1, '', 'd53cf417-84bc-4a72-8acb-28367f41bfbb'),\r\n(172, 'Cape Town', -33.92584000, 18.42322000, '661acdad-94d4-4b5a-b15f-5b6e7a1579b1', 'Q5465', '', '', '', '', 1, '', '2025-03-28 08:46:38', '', 1, '', 'a2015ded-0fed-4064-8e63-83a495e1a09b'),\r\n(173, 'Epupa Constituency', -17.00388000, 13.24825000, 'b1563d67-cc43-430c-b1c4-f3c38d7c17fb', 'Q1026511', '', '', '', '', 1, '', '2025-03-28 08:50:40', '', 1, '', 'a55f8d5a-f41f-4b0d-b6a4-69726477fc52'),\r\n(174, 'Khorixas', -20.36667000, 14.96667000, 'd6a38115-777b-4a34-9c1c-02b8cb575615', 'Q1740681', '', '', '', '', 1, '', '2025-03-28 08:50:40', '', 1, '', 'a55f8d5a-f41f-4b0d-b6a4-69726477fc52'),\r\n(175, 'Khorixas Constituency', -20.36792000, 14.95996000, '95da731e-056c-4a0c-8e83-27f4ce5af61e', 'Q4122340', '', '', '', '', 1, '', '2025-03-28 08:50:40', '', 1, '', 'a55f8d5a-f41f-4b0d-b6a4-69726477fc52'),\r\n(176, 'Opuwo', -18.06068000, 13.83998000, 'efb189f4-ec1a-4c37-87ab-ef87e8eb1cf4', 'Q1024089', '', '', '', '', 1, '', '2025-03-28 08:50:40', '', 1, '', 'a55f8d5a-f41f-4b0d-b6a4-69726477fc52'),\r\n(177, 'Opuwo Constituency', -20.11667000, 16.15000000, '8d7c361f-e6fa-4b0c-b061-0351604ff13a', 'Q1704346', '', '', '', '', 1, '', '2025-03-28 08:51:56', '', 1, '', 'a55f8d5a-f41f-4b0d-b6a4-69726477fc52'),\r\n(178, 'Sesfontein Constituency', -19.56106000, 13.76530000, '5458d615-f674-4714-9f0b-1e7a37bc3ea1', 'Q3711708', '', '', '', '', 1, '', '2025-03-28 08:51:56', '', 1, '', 'a55f8d5a-f41f-4b0d-b6a4-69726477fc52'),\r\n(179, 'Ohangwena', -17.40000000, 15.88333000, 'f5527d58-5f23-41cf-9fe0-4ef9b91bcecf', 'Q2033319', '', '', '', '', 1, '', '2025-03-28 08:55:08', '', 1, '', '3ee5b10e-60d4-4eb0-a5ea-ae98db45bebe'),\r\n(180, 'Gobabis', -22.45000000, 18.96667000, '00c5000a-3742-450c-a52b-9ba38913e945', 'Q1000609', '', '', '', '', 1, '', '2025-03-28 08:59:33', '', 1, '', 'ab88842f-0e66-47cd-9712-6d5aad3b179b'),\r\n(181, 'Ongandjera', -17.88333000, 15.06667000, '2f13683a-9863-483c-ba88-170d5a78b9d8', 'Q3352721', '', '', '', '', 1, '', '2025-03-28 09:01:58', '', 1, '', 'dd015fe7-50b9-4a1e-be66-2e5deb6ea05e'),\r\n(182, 'Outapi', -17.50000000, 14.98333000, 'cd22e1e9-eb6f-42e1-90d6-ea8aa07e2753', 'Q1758215', '', '', '', '', 1, '', '2025-03-28 09:01:58', '', 1, '', 'dd015fe7-50b9-4a1e-be66-2e5deb6ea05e'),\r\n(183, 'Ondangwa', -17.91667000, 15.95000000, '589cbcbc-9dc5-4880-968d-c380fd4316ef', 'Q2023773', '', '', '', '', 1, '', '2025-03-28 09:05:53', '', 1, '', '6f114d13-ce7f-4751-8029-ff7723a932a2'),\r\n(184, 'Ongwediva', -17.78333000, 15.76667000, '6ae4f351-55e2-4e69-a31e-29e76ac7f7c5', 'Q841557', '', '', '', '', 1, '', '2025-03-28 09:05:53', '', 1, '', '6f114d13-ce7f-4751-8029-ff7723a932a2'),\r\n(185, 'Oshakati', -17.78833000, 15.70436000, '5ebe20b5-2468-4ef9-ab82-37e554d39d5f', 'Q985622', '', '', '', '', 1, '', '2025-03-28 09:05:53', '', 1, '', '6f114d13-ce7f-4751-8029-ff7723a932a2'),\r\n(186, 'Omuthiya', -18.36463000, 16.58146000, 'd888b4d2-af86-4e34-8bee-4554e0b19213', 'Q1005584', '', '', '', '', 1, '', '2025-03-28 09:09:23', '', 1, '', 'b0650a6d-56d8-4765-b566-f6b93255f7f4'),\r\n(187, 'Tsumeb', -19.23333000, 17.71667000, '96b51507-1b66-4b5c-ab37-909159d53261', 'Q639467', '', '', '', '', 1, '', '2025-03-28 09:09:23', '', 1, '', 'b0650a6d-56d8-4765-b566-f6b93255f7f4'),\r\n(188, 'Bagani', -18.11065000, 21.61645000, 'b28199b8-c1d9-47c5-836a-fab2823a726b', 'Q799830', '', '', '', '', 1, '', '2025-03-28 09:13:31', '', 1, '', 'edc3add6-1977-443e-af40-36f700ad31c0'),\r\n(189, 'Katima Mulilo', -17.50000000, 24.26667000, 'aa720304-b89b-4170-8539-0f476d770284', 'Q864100', '', '', '', '', 1, '', '2025-03-28 09:13:31', '', 1, '', 'edc3add6-1977-443e-af40-36f700ad31c0');",
    "add_category_submenu": 1,
    "php_ajaxmethod": "",
    "add_php_getitem": 0,
    "add_php_getitems": 0,
    "add_css_view": 0,
    "add_php_getitems_after_all": 0,
    "css_view": "",
    "add_php_getlistquery": 0,
    "add_css_views": 0,
    "add_php_getform": 1,
    "css_views": "",
    "add_php_before_save": 1,
    "add_javascript_view_file": 0,
    "add_php_save": 0,
    "javascript_view_file": "",
    "add_php_postsavehook": 0,
    "add_javascript_view_footer": 0,
    "add_php_allowadd": 0,
    "javascript_view_footer": "",
    "add_php_allowedit": 0,
    "add_javascript_views_file": 0,
    "add_php_before_cancel": 0,
    "javascript_views_file": "",
    "add_php_after_cancel": 0,
    "add_javascript_views_footer": 0,
    "add_php_batchcopy": 0,
    "javascript_views_footer": "",
    "add_php_batchmove": 0,
    "add_custom_button": 1,
    "add_php_before_publish": 0,
    "custom_button": null,
    "add_php_after_publish": 0,
    "php_controller": "[CUSTOMCODE=formControllerEdit]",
    "add_php_before_delete": 0,
    "php_model": "",
    "add_php_after_delete": 0,
    "php_controller_list": "",
    "add_php_document": 0,
    "php_model_list": "",
    "mysql_table_engine": "InnoDB",
    "add_view_toolbar": 0,
    "mysql_table_collate": "utf8mb4_unicode_ci",
    "view_toolbar": null,
    "add_sql": 1,
    "add_views_toolbar": 0,
    "views_toolbar": null,
    "guid": "3dbb581b-619a-4fb0-a6f6-e4a136ea31e2",
    "add_php_ajax": 0,
    "@dependencies": [
        {
            "key": "admin_view",
            "value": "3dbb581b-619a-4fb0-a6f6-e4a136ea31e2",
            "entity": "admin_fields",
            "table": "#__componentbuilder_admin_fields",
            "direction": "in"
        },
        {
            "key": "function_name",
            "value": "saveGUIDPower",
            "entity": "custom_code",
            "table": "#__componentbuilder_custom_code",
            "direction": "out"
        },
        {
            "key": "function_name",
            "value": "setGUIDFormPower",
            "entity": "custom_code",
            "table": "#__componentbuilder_custom_code",
            "direction": "out"
        },
        {
            "key": "function_name",
            "value": "formControllerEdit",
            "entity": "custom_code",
            "table": "#__componentbuilder_custom_code",
            "direction": "out"
        },
        {
            "key": "9bb478ed-3893-5c51-a67e-132879977f33.png",
            "pointer": "9bb478ed-3893-5c51-a67e-132879977f33--png",
            "value": "images\/vdm\/icon\/city.png",
            "entity": "file",
            "table": "file_system",
            "target": "images"
        }
    ]
}